safety/__init__.py
safety/__main__.py
safety/cli.py
safety/errors.py
safety/formatter.py
safety/parser.py
safety/safety.py
safety_cli-0.0.4.dist-info/DESCRIPTION.rst
safety_cli-0.0.4.dist-info/METADATA
safety_cli-0.0.4.dist-info/RECORD
safety_cli-0.0.4.dist-info/WHEEL
safety_cli-0.0.4.dist-info/entry_points.txt
safety_cli-0.0.4.dist-info/metadata.json
safety_cli-0.0.4.dist-info/top_level.txt
