Metadata-Version: 2.0
Name: safety-cli
Version: 0.0.4
Summary: Safety checks your installed dependencies for known security vulnerabilities
Home-page: https://safetydb.io
Author: safetydb.io
Author-email: hi@safetydb.io
License: MIT license
Keywords: safety
Platform: UNKNOWN
Classifier: Development Status :: 2 - Pre-Alpha
Classifier: Intended Audience :: Developers
Classifier: License :: OSI Approved :: MIT License
Classifier: Natural Language :: English
Classifier: Programming Language :: Python :: 2
Classifier: Programming Language :: Python :: 2.6
Classifier: Programming Language :: Python :: 2.7
Classifier: Programming Language :: Python :: 3
Classifier: Programming Language :: Python :: 3.3
Classifier: Programming Language :: Python :: 3.4
Classifier: Programming Language :: Python :: 3.5
Requires-Dist: Click (>=6.0)
Requires-Dist: requests
Requires-Dist: packaging
